XStatic_Bootstrap_Datepicker-1.4.0.0-py3.6-nspkg.pth
xstatic/pkg/bootstrap_datepicker/__init__.py
xstatic/pkg/bootstrap_datepicker/data/bootstrap-datepicker.js
xstatic/pkg/bootstrap_datepicker/data/bootstrap-datepicker.standalone.css
xstatic/pkg/bootstrap_datepicker/data/bootstrap-datepicker3.standalone.css
xstatic/pkg/bootstrap_datepicker/data/datepicker.css
xstatic/pkg/bootstrap_datepicker/data/datepicker3.css
xstatic/pkg/bootstrap_datepicker/data/locales/bootstrap-datepicker.ar.js
xstatic/pkg/bootstrap_datepicker/data/locales/bootstrap-datepicker.az.js
xstatic/pkg/bootstrap_datepicker/data/locales/bootstrap-datepicker.bg.js
xstatic/pkg/bootstrap_datepicker/data/locales/bootstrap-datepicker.bs.js
xstatic/pkg/bootstrap_datepicker/data/locales/bootstrap-datepicker.ca.js
xstatic/pkg/bootstrap_datepicker/data/locales/bootstrap-datepicker.cs.js
xstatic/pkg/bootstrap_datepicker/data/locales/bootstrap-datepicker.cy.js
xstatic/pkg/bootstrap_datepicker/data/locales/bootstrap-datepicker.da.js
xstatic/pkg/bootstrap_datepicker/data/locales/bootstrap-datepicker.de.js
xstatic/pkg/bootstrap_datepicker/data/locales/bootstrap-datepicker.el.js
xstatic/pkg/bootstrap_datepicker/data/locales/bootstrap-datepicker.en-GB.js
xstatic/pkg/bootstrap_datepicker/data/locales/bootstrap-datepicker.es.js
xstatic/pkg/bootstrap_datepicker/data/locales/bootstrap-datepicker.et.js
xstatic/pkg/bootstrap_datepicker/data/locales/bootstrap-datepicker.eu.js
xstatic/pkg/bootstrap_datepicker/data/locales/bootstrap-datepicker.fa.js
xstatic/pkg/bootstrap_datepicker/data/locales/bootstrap-datepicker.fi.js
xstatic/pkg/bootstrap_datepicker/data/locales/bootstrap-datepicker.fo.js
xstatic/pkg/bootstrap_datepicker/data/locales/bootstrap-datepicker.fr-CH.js
xstatic/pkg/bootstrap_datepicker/data/locales/bootstrap-datepicker.fr.js
xstatic/pkg/bootstrap_datepicker/data/locales/bootstrap-datepicker.gl.js
xstatic/pkg/bootstrap_datepicker/data/locales/bootstrap-datepicker.he.js
XStatic_Bootstrap_Datepicker-1.4.0.0.dist-info/METADATA
XStatic_Bootstrap_Datepicker-1.4.0.0.dist-info/WHEEL
XStatic_Bootstrap_Datepicker-1.4.0.0.dist-info/namespace_packages.txt
XStatic_Bootstrap_Datepicker-1.4.0.0.dist-info/top_level.txt
XStatic_Bootstrap_Datepicker-1.4.0.0.dist-info/RECORD
