Metadata-Version: 2.1
Name: XStatic-Bootstrap-Datepicker
Version: 1.4.0.0
Summary: Bootstrap-Datepicker 1.4.0 (XStatic packaging standard)
Home-page: https://github.com/eternicode/bootstrap-datepicker/
Maintainer: Radomir Dopieralski
Maintainer-email: openstack@sheep.art.pl
License: (same as Bootstrap-Datepicker)
Keywords: bootstrap_datepicker xstatic
Platform: any
